mcp_ohmy_sql/__init__.py
mcp_ohmy_sql/_version.py
mcp_ohmy_sql/adapter/__init__.py
mcp_ohmy_sql/adapter/adapter.py
mcp_ohmy_sql/adapter/adapter_init.py
mcp_ohmy_sql/adapter/api.py
mcp_ohmy_sql/adapter/aws_redshift_adapter.py
mcp_ohmy_sql/adapter/relational_adapter.py
mcp_ohmy_sql/adapter/tool_adapter.py
mcp_ohmy_sql/api.py
mcp_ohmy_sql/app.py
mcp_ohmy_sql/aws/__init__.py
mcp_ohmy_sql/aws/api.py
mcp_ohmy_sql/aws/aws_redshift/__init__.py
mcp_ohmy_sql/aws/aws_redshift/api.py
mcp_ohmy_sql/aws/aws_redshift/query.py
mcp_ohmy_sql/aws/aws_redshift/utils.py
mcp_ohmy_sql/config/__init__.py
mcp_ohmy_sql/config/api.py
mcp_ohmy_sql/config/aws_redshift.py
mcp_ohmy_sql/config/boto_session.py
mcp_ohmy_sql/config/conn.py
mcp_ohmy_sql/config/define.py
mcp_ohmy_sql/config/init.py
mcp_ohmy_sql/config/sqlalchemy.py
mcp_ohmy_sql/constants.py
mcp_ohmy_sql/create_app.py
mcp_ohmy_sql/db/__init__.py
mcp_ohmy_sql/db/aws_redshift/__init__.py
mcp_ohmy_sql/db/aws_redshift/api.py
mcp_ohmy_sql/db/aws_redshift/schema_1_model.py
mcp_ohmy_sql/db/aws_redshift/schema_2_encoder.py
mcp_ohmy_sql/db/aws_redshift/schema_3_extractor.py
mcp_ohmy_sql/db/aws_redshift/sql/__init__.py
mcp_ohmy_sql/db/aws_redshift/sql/column_info.sql
mcp_ohmy_sql/db/aws_redshift/sql/schema_info.sql
mcp_ohmy_sql/db/aws_redshift/sql/table_info.sql
mcp_ohmy_sql/db/aws_redshift/tpl/__init__.py
mcp_ohmy_sql/db/aws_redshift/tpl/database_info.jinja
mcp_ohmy_sql/db/aws_redshift/tpl/schema_info.jinja
mcp_ohmy_sql/db/aws_redshift/tpl/table_info.jinja
mcp_ohmy_sql/db/metadata.py
mcp_ohmy_sql/db/relational/__init__.py
mcp_ohmy_sql/db/relational/api.py
mcp_ohmy_sql/db/relational/schema_1_model.py
mcp_ohmy_sql/db/relational/schema_2_encoder.py
mcp_ohmy_sql/db/relational/schema_3_extractor.py
mcp_ohmy_sql/docs/__init__.py
mcp_ohmy_sql/docs/mcp_instructions.md
mcp_ohmy_sql/lazy_import.py
mcp_ohmy_sql/logger.py
mcp_ohmy_sql/paths.py
mcp_ohmy_sql/sa/__init__.py
mcp_ohmy_sql/sa/api.py
mcp_ohmy_sql/sa/query.py
mcp_ohmy_sql/sa/utils.py
mcp_ohmy_sql-0.1.4.dist-info/AUTHORS.rst
mcp_ohmy_sql-0.1.4.dist-info/LICENSE.txt
mcp_ohmy_sql-0.1.4.dist-info/METADATA
mcp_ohmy_sql-0.1.4.dist-info/WHEEL
mcp_ohmy_sql-0.1.4.dist-info/entry_points.txt
mcp_ohmy_sql-0.1.4.dist-info/RECORD
