Metadata-Version: 2.3
Name: mcp_ohmy_sql
Version: 0.1.4
Summary: A powerful Model Context Protocol (MCP) server that provides universal SQL database connectivity with intelligent query optimization, schema introspection, and built-in safety features for AI assistants.
License: AGPL-3.0-or-later
Author: Sanhe Hu, Jiazhen Zhu
Author-email: husanhe@email.com
Maintainer: Sanhe Hu, Jiazhen Zhu
Maintainer-email: husanhe@email.com
Requires-Python: >=3.10,<4.0
Classifier: License :: OSI Approved :: GNU Affero General Public License v3 or later (AGPLv3+)
Classifier: Programming Language :: Python :: 3
Classifier: Programming Language :: Python :: 3.10
Classifier: Programming Language :: Python :: 3.11
Classifier: Programming Language :: Python :: 3.12
Classifier: Programming Language :: Python :: 3.13
Provides-Extra: auto
Provides-Extra: aws
Provides-Extra: aws-redshift
Provides-Extra: dev
Provides-Extra: doc
Provides-Extra: mssql
Provides-Extra: mysql
Provides-Extra: oracle
Provides-Extra: postgres
Provides-Extra: sqlite
Provides-Extra: test
Requires-Dist: PyMySQL (>=1.1.1,<2.0.0) ; extra == "mysql"
Requires-Dist: Sphinx (>=7.4.7,<8.0.0) ; extra == "doc"
Requires-Dist: aws-cdk-lib (>=2.179.0,<2.180.0) ; extra == "dev"
Requires-Dist: aws_sdk_polars (>=0.1.4,<1.0.0) ; extra == "test"
Requires-Dist: boto3 (>=1.37.38,<2.0.0) ; extra == "aws"
Requires-Dist: boto3 (>=1.37.38,<2.0.0) ; extra == "aws-redshift"
Requires-Dist: boto3 (>=1.37.38,<2.0.0) ; extra == "dev"
Requires-Dist: boto3 (>=1.37.38,<2.0.0) ; extra == "test"
Requires-Dist: boto_session_manager (>=1.8.1,<2.0.0) ; extra == "aws"
Requires-Dist: boto_session_manager (>=1.8.1,<2.0.0) ; extra == "aws-redshift"
Requires-Dist: boto_session_manager (>=1.8.1,<2.0.0) ; extra == "dev"
Requires-Dist: boto_session_manager (>=1.8.1,<2.0.0) ; extra == "test"
Requires-Dist: build (>=1.2.1,<2.0.0) ; extra == "dev"
Requires-Dist: cdk_mate (>=0.1.6,<1.0.0) ; extra == "dev"
Requires-Dist: claude-desktop-config (>=0.2.1,<1.0.0) ; extra == "dev"
Requires-Dist: diskcache (>=5.6.3,<6.0.0)
Requires-Dist: docfly (==3.0.0) ; extra == "doc"
Requires-Dist: enum_mate (>=0.1.1,<1.0.0)
Requires-Dist: furo (==2024.8.6) ; extra == "doc"
Requires-Dist: ipython (>=8.18.1,<8.19.0) ; extra == "doc"
Requires-Dist: jinja2 (>=3.0.0,<4.0.0) ; extra == "aws-redshift"
Requires-Dist: jinja2 (>=3.0.0,<4.0.0) ; extra == "test"
Requires-Dist: mcp[cli] (>=1.9.3,<2.0.0)
Requires-Dist: nbsphinx (>=0.8.12,<1.0.0) ; extra == "doc"
Requires-Dist: oracledb (>=3.0.0,<4.0.0) ; extra == "oracle"
Requires-Dist: polars (>=1.27.1,<2.0.0) ; extra == "dev"
Requires-Dist: psycopg2-binary (>=2.9.1,<3.0.0) ; extra == "postgres"
Requires-Dist: pygments (>=2.18.0,<3.0.0) ; extra == "doc"
Requires-Dist: pymssql (>2.3.0,<3.0.0) ; extra == "mssql"
Requires-Dist: pytest (>=8.2.2,<9.0.0) ; extra == "test"
Requires-Dist: pytest-asyncio (>=1.0.0,<2.0.0) ; extra == "test"
Requires-Dist: pytest-cov (>=6.0.0,<7.0.0) ; extra == "test"
Requires-Dist: redshift_connector (>=2.1.0,<3.0.0) ; extra == "aws-redshift"
Requires-Dist: redshift_connector (>=2.1.0,<3.0.0) ; extra == "test"
Requires-Dist: requests (>=2.32.3,<3.0.0) ; extra == "test"
Requires-Dist: rich (>=13.8.1,<14.0.0) ; extra == "dev"
Requires-Dist: rstobj (==1.2.1) ; extra == "doc"
Requires-Dist: s3pathlib (>=2.3.3,<3.0.0) ; extra == "aws-redshift"
Requires-Dist: s3pathlib (>=2.3.3,<3.0.0) ; extra == "test"
Requires-Dist: simple_aws_redshift (>=0.3.1,<1.0.0) ; extra == "aws-redshift"
Requires-Dist: simple_aws_redshift (>=0.3.1,<1.0.0) ; extra == "test"
Requires-Dist: sphinx-copybutton (>=0.5.2,<1.0.0) ; extra == "doc"
Requires-Dist: sphinx-design (>=0.6.1,<1.0.0) ; extra == "doc"
Requires-Dist: sphinx-jinja (>=2.0.2,<3.0.0) ; extra == "doc"
Requires-Dist: sqlalchemy (>=2.0.33,<3.0.0)
Requires-Dist: sqlalchemy_mate (>=2.0.0.3,<3.0.0.0) ; extra == "dev"
Requires-Dist: tabulate (>=0.9.0,<1.0.0)
Requires-Dist: twine (>=6.0.0,<7.0.0) ; extra == "dev"
Requires-Dist: vislog (>=0.1.2,<1.0.0)
Requires-Dist: vislog (>=0.1.2,<1.0.0) ; extra == "dev"
Requires-Dist: wheel (>=0.45.0,<1.0.0) ; extra == "dev"
Requires-Dist: which_runtime (>=0.1.1,<1.0.0)
Project-URL: Changelog, https://github.com/MacHu-GWU/mcp_ohmy_sql-project/blob/main/release-history.rst
Project-URL: Documentation, https://mcp-ohmy-sql.readthedocs.io/en/latest/
Project-URL: Download, https://pypi.org/pypi/mcp-ohmy-sql#files
Project-URL: Homepage, https://github.com/MacHu-GWU/mcp_ohmy_sql-project
Project-URL: Issues, https://github.com/MacHu-GWU/mcp_ohmy_sql-project/issues
Project-URL: Repository, https://github.com/MacHu-GWU/mcp_ohmy_sql-project
